passmeter/__main__.py
passmeter/cli.py
passmeter-0.1.2.dist-info/METADATA
passmeter-0.1.2.dist-info/WHEEL
passmeter-0.1.2.dist-info/entry_points.txt
passmeter-0.1.2.dist-info/top_level.txt
passmeter-0.1.2.dist-info/RECORD
