Metadata-Version: 2.4
Name: passmeter
Version: 0.1.2
Summary: Ferramenta de análise de força de senhas
Requires-Python: >=3.8
Requires-Dist: colorama
Requires-Dist: tabulate
Requires-Dist: zxcvbn
